README.md
setup.py
surfer/__init__.py
surfer/surfer.py
surfer.egg-info/PKG-INFO
surfer.egg-info/SOURCES.txt
surfer.egg-info/dependency_links.txt
surfer.egg-info/top_level.txt