Metadata-Version: 2.1
Name: surfer
Version: 0.0.1
Summary: surF - Fourier surrogate modeling
Home-page: https://github.com/pypa/surfer
Author: Marco S. Nobile
Author-email: m.s.nobile@tue.nl
License: LICENSE.txt
Platform: UNKNOWN
Classifier: Programming Language :: Python :: 3
Classifier: Operating System :: OS Independent
Requires-Python: >=3.6
